ceda_datapoint/__init__.py
ceda_datapoint/config/mapper_example.json
ceda_datapoint/core/__init__.py
ceda_datapoint/core/asset.py
ceda_datapoint/core/client.py
ceda_datapoint/core/cloud.py
ceda_datapoint/core/item.py
ceda_datapoint/design.md
ceda_datapoint/engine/__init__.py
ceda_datapoint/engine/combine.py
ceda_datapoint/engine/store.py
ceda_datapoint/mixins/__init__.py
ceda_datapoint/mixins/general.py
ceda_datapoint/mixins/properties.py
ceda_datapoint/tests/__init__.py
ceda_datapoint/tests/test_client.py
ceda_datapoint/tests/test_cloud.py
ceda_datapoint/tests/test_item.py
ceda_datapoint/tests/test_select.py
ceda_datapoint/utils.py
ceda_datapoint-0.5.2.dist-info/LICENSE
ceda_datapoint-0.5.2.dist-info/METADATA
ceda_datapoint-0.5.2.dist-info/WHEEL
ceda_datapoint-0.5.2.dist-info/RECORD
