Metadata-Version: 2.3
Name: ceda-datapoint
Version: 0.5.2
Summary: Datapoint provides python-based search/access tools for using data primarily from the CEDA Archive.
License: BSD 3
Author: Daniel Westwood
Author-email: daniel.westwood@stfc.ac.uk
Requires-Python: >=3.9,<4
Classifier: License :: Other/Proprietary License
Classifier: Programming Language :: Python :: 3
Classifier: Programming Language :: Python :: 3.9
Classifier: Programming Language :: Python :: 3.10
Classifier: Programming Language :: Python :: 3.11
Classifier: Programming Language :: Python :: 3.12
Classifier: Programming Language :: Python :: 3.13
Requires-Dist: aiohttp (>=3.11.7,<4.0.0)
Requires-Dist: cfapyx (>=2025.6.23)
Requires-Dist: fsspec (>=2024.9.0)
Requires-Dist: kerchunk (>=0.2.6,<0.3.0)
Requires-Dist: pystac-client (>=0.7)
Requires-Dist: requests (>=2.32.3,<3.0.0)
Requires-Dist: rioxarray (>=0.15.0)
Requires-Dist: xarray (>=2024.6.0)
Requires-Dist: xdoctest (>=1.2.0,<2.0.0)
Requires-Dist: zarr (>=2.15.0,<3.1)
